pocketwatch/__init__.py
pocketwatch/core.py
pocketwatch/decorators.py
pocketwatch/spellbook.py
pocketwatch/data/ding.wav
pocketwatch/data/meteor.wav
pocketwatch-0.1.1.dist-info/licenses/LICENSE
pocketwatch-0.1.1.dist-info/METADATA
pocketwatch-0.1.1.dist-info/WHEEL
pocketwatch-0.1.1.dist-info/top_level.txt
pocketwatch-0.1.1.dist-info/RECORD
