Metadata-Version: 2.4
Name: pocketwatch
Version: 0.1.1
Summary: Drop-in stopwatch utility
Author-email: tmarquart <tmarquart@gmail.com>
License: MIT
Requires-Python: >=3.9
License-File: LICENSE
Requires-Dist: notify-py>=0.3
Dynamic: license-file
